treer_sso_sdk/__init__.py
treer_sso_sdk/client.py
treer_sso_sdk/config.py
treer_sso_sdk/exceptions.py
treer_sso_sdk/http_client.py
treer_sso_sdk/interfaces.py
treer_sso_sdk/models.py
treer_sso_sdk/utils.py
treer_sso_sdk-1.0.0.dist-info/licenses/LICENSE
treer_sso_sdk-1.0.0.dist-info/METADATA
treer_sso_sdk-1.0.0.dist-info/WHEEL
treer_sso_sdk-1.0.0.dist-info/top_level.txt
treer_sso_sdk-1.0.0.dist-info/RECORD
