Metadata-Version: 2.4
Name: treer-sso-sdk
Version: 1.0.0
Summary: Treer SSO SDK - OAuth 2.0客户端SDK，用于快速集成Treer SSO服务
Author-email: Treer Team <dev@treer.ru>
Maintainer-email: Treer Team <dev@treer.ru>
License-Expression: MIT
Project-URL: Homepage, https://github.com/treer-ru/treer-sso-sdk
Project-URL: Documentation, https://treer-sso-sdk.readthedocs.io/
Project-URL: Repository, https://github.com/treer-ru/treer-sso-sdk.git
Project-URL: Bug Reports, https://github.com/treer-ru/treer-sso-sdk/issues
Project-URL: Changelog, https://github.com/treer-ru/treer-sso-sdk/blob/main/CHANGELOG.md
Keywords: sso,oauth,oauth2,authentication,treer
Classifier: Development Status :: 5 - Production/Stable
Classifier: Intended Audience :: Developers
Classifier: Operating System :: OS Independent
Classifier: Programming Language :: Python :: 3
Classifier: Programming Language :: Python :: 3.11
Classifier: Programming Language :: Python :: 3.12
Classifier: Topic :: Software Development :: Libraries :: Python Modules
Classifier: Topic :: Internet :: WWW/HTTP :: HTTP Servers
Classifier: Topic :: System :: Systems Administration :: Authentication/Directory
Requires-Python: >=3.11
License-File: LICENSE
Requires-Dist: httpx>=0.13.0
Provides-Extra: dev
Requires-Dist: pytest>=7.0.0; extra == "dev"
Requires-Dist: pytest-asyncio>=0.21.0; extra == "dev"
Requires-Dist: pytest-cov>=4.0.0; extra == "dev"
Requires-Dist: black>=23.0.0; extra == "dev"
Requires-Dist: isort>=5.12.0; extra == "dev"
Requires-Dist: flake8>=6.0.0; extra == "dev"
Requires-Dist: mypy>=1.0.0; extra == "dev"
Requires-Dist: pre-commit>=3.0.0; extra == "dev"
Provides-Extra: docs
Requires-Dist: sphinx>=6.0.0; extra == "docs"
Requires-Dist: sphinx-rtd-theme>=1.2.0; extra == "docs"
Dynamic: license-file
